llmbuilder/__init__.py
llmbuilder/__main__.py
llmbuilder/py.typed
llmbuilder/cli/__init__.py
llmbuilder/cli/config.py
llmbuilder/cli/data.py
llmbuilder/cli/deploy.py
llmbuilder/cli/eval.py
llmbuilder/cli/fast_main.py
llmbuilder/cli/help.py
llmbuilder/cli/inference.py
llmbuilder/cli/init.py
llmbuilder/cli/main.py
llmbuilder/cli/migrate.py
llmbuilder/cli/model.py
llmbuilder/cli/monitor.py
llmbuilder/cli/optimize.py
llmbuilder/cli/pipeline.py
llmbuilder/cli/tools.py
llmbuilder/cli/train.py
llmbuilder/cli/ultra_fast.py
llmbuilder/cli/upgrade.py
llmbuilder/cli/vocab.py
llmbuilder/compat/__init__.py
llmbuilder/compat/config_migration.py
llmbuilder/compat/deprecation.py
llmbuilder/compat/legacy_imports.py
llmbuilder/compat/project_migrator.py
llmbuilder/compat/script_wrapper.py
llmbuilder/core/__init__.py
llmbuilder/core/data/__init__.py
llmbuilder/core/data/dedup.py
llmbuilder/core/data/ingest.py
llmbuilder/core/deployment/__init__.py
llmbuilder/core/deployment/mobile.py
llmbuilder/core/deployment/packager.py
llmbuilder/core/deployment/server.py
llmbuilder/core/eval/__init__.py
llmbuilder/core/eval/eval.py
llmbuilder/core/finetune/__init__.py
llmbuilder/core/finetune/finetune.py
llmbuilder/core/finetune/peft_config.py
llmbuilder/core/finetune/peft_model_utils.py
llmbuilder/core/finetune/peft_model_wrapper.py
llmbuilder/core/inference/__init__.py
llmbuilder/core/inference/engine.py
llmbuilder/core/inference/history.py
llmbuilder/core/inference/templates.py
llmbuilder/core/model/__init__.py
llmbuilder/core/model/gpt_model.py
llmbuilder/core/model/simple_transformer.py
llmbuilder/core/monitoring/__init__.py
llmbuilder/core/monitoring/dashboard.py
llmbuilder/core/monitoring/diagnostics.py
llmbuilder/core/monitoring/logs.py
llmbuilder/core/monitoring/metrics.py
llmbuilder/core/tools/__init__.py
llmbuilder/core/tools/conversion_pipeline.py
llmbuilder/core/tools/download_hf_model.py
llmbuilder/core/tools/export_gguf.py
llmbuilder/core/tools/generate_model_card.py
llmbuilder-1.0.3.dist-info/METADATA
llmbuilder-1.0.3.dist-info/WHEEL
llmbuilder-1.0.3.dist-info/entry_points.txt
llmbuilder-1.0.3.dist-info/top_level.txt
llmbuilder-1.0.3.dist-info/RECORD
