Metadata-Version: 2.4
Name: llmbuilder
Version: 1.0.3
Summary: Complete LLM Training and Deployment Pipeline with CLI
Author-email: Qubase <contact@qubase.in>
Maintainer-email: Qubase Team <support@qubase.in>
License: MIT
Project-URL: Homepage, https://github.com/qubase/llmbuilder
Project-URL: Documentation, https://llmbuilder.readthedocs.io
Project-URL: Repository, https://github.com/qubase/llmbuilder
Project-URL: Issues, https://github.com/qubase/llmbuilder/issues
Project-URL: Changelog, https://github.com/qubase/llmbuilder/blob/main/CHANGELOG.md
Keywords: llm,training,fine-tuning,machine-learning,ai,transformers,cli,pytorch,huggingface,gpt,llama,deployment,inference
Classifier: Development Status :: 4 - Beta
Classifier: Intended Audience :: Developers
Classifier: Intended Audience :: Science/Research
Classifier: License :: OSI Approved :: MIT License
Classifier: Operating System :: OS Independent
Classifier: Programming Language :: Python :: 3
Classifier: Programming Language :: Python :: 3.8
Classifier: Programming Language :: Python :: 3.9
Classifier: Programming Language :: Python :: 3.10
Classifier: Programming Language :: Python :: 3.11
Classifier: Programming Language :: Python :: 3.12
Classifier: Topic :: Scientific/Engineering :: Artificial Intelligence
Classifier: Topic :: Software Development :: Libraries :: Python Modules
Classifier: Topic :: Text Processing :: Linguistic
Classifier: Environment :: Console
Classifier: Framework :: FastAPI
Requires-Python: >=3.8
Requires-Dist: torch<3.0.0,>=2.0.0
Requires-Dist: transformers<5.0.0,>=4.35.0
Requires-Dist: tokenizers<1.0.0,>=0.13.0
Requires-Dist: sentencepiece<1.0.0,>=0.1.99
Requires-Dist: click>=8.0.0
Requires-Dist: rich>=13.0.0
Requires-Dist: tqdm>=4.65.0
Requires-Dist: fastapi>=0.100.0
Requires-Dist: uvicorn>=0.20.0
Requires-Dist: pydantic>=2.0.0
Requires-Dist: pandas<3.0.0,>=2.0.0
Requires-Dist: numpy<2.0.0,>=1.24.0
Requires-Dist: PyMuPDF<2.0.0,>=1.23.0
Requires-Dist: docx2txt<1.0.0,>=0.8
Requires-Dist: python-pptx<1.0.0,>=0.6.21
Requires-Dist: markdown<4.0.0,>=3.4.0
Requires-Dist: beautifulsoup4<5.0.0,>=4.12.0
Requires-Dist: ebooklib<1.0.0,>=0.18
Requires-Dist: pytesseract<1.0.0,>=0.3.10
Requires-Dist: Pillow<11.0.0,>=9.0.0
Requires-Dist: requests<3.0.0,>=2.28.0
Requires-Dist: sentence-transformers<3.0.0,>=2.2.0
Requires-Dist: scikit-learn<2.0.0,>=1.3.0
Requires-Dist: xxhash<4.0.0,>=3.0.0
Requires-Dist: langdetect<2.0.0,>=1.0.9
Requires-Dist: loguru<1.0.0,>=0.7.0
Requires-Dist: PyYAML<7.0.0,>=6.0
Requires-Dist: jsonschema<5.0.0,>=4.17.0
Requires-Dist: psutil>=5.9.0
Requires-Dist: reportlab<5.0.0,>=3.6.0
Provides-Extra: dev
Requires-Dist: pytest>=7.0.0; extra == "dev"
Requires-Dist: pytest-cov>=4.0.0; extra == "dev"
Requires-Dist: pytest-asyncio>=0.21.0; extra == "dev"
Requires-Dist: pytest-xdist>=3.0.0; extra == "dev"
Requires-Dist: pytest-timeout>=2.1.0; extra == "dev"
Requires-Dist: pytest-benchmark>=4.0.0; extra == "dev"
Requires-Dist: black>=23.0.0; extra == "dev"
Requires-Dist: isort>=5.12.0; extra == "dev"
Requires-Dist: flake8>=6.0.0; extra == "dev"
Requires-Dist: mypy>=1.0.0; extra == "dev"
Requires-Dist: pre-commit>=3.0.0; extra == "dev"
Requires-Dist: build>=0.10.0; extra == "dev"
Requires-Dist: twine>=4.0.0; extra == "dev"
Provides-Extra: gpu
Requires-Dist: peft<1.0.0,>=0.6.0; extra == "gpu"
Requires-Dist: bitsandbytes<1.0.0,>=0.41.0; extra == "gpu"
Requires-Dist: accelerate<1.0.0,>=0.24.0; extra == "gpu"
Requires-Dist: flash-attn<3.0.0,>=2.0.0; sys_platform != "darwin" and extra == "gpu"
Provides-Extra: docs
Requires-Dist: sphinx>=5.0.0; extra == "docs"
Requires-Dist: sphinx-rtd-theme>=1.2.0; extra == "docs"
Requires-Dist: myst-parser>=0.18.0; extra == "docs"
Requires-Dist: sphinx-click>=4.0.0; extra == "docs"
Requires-Dist: sphinx-autodoc-typehints>=1.19.0; extra == "docs"
Provides-Extra: test
Requires-Dist: pytest>=7.0.0; extra == "test"
Requires-Dist: pytest-cov>=4.0.0; extra == "test"
Requires-Dist: pytest-asyncio>=0.21.0; extra == "test"
Requires-Dist: pytest-xdist>=3.0.0; extra == "test"
Requires-Dist: pytest-timeout>=2.1.0; extra == "test"
Provides-Extra: monitoring
Requires-Dist: wandb>=0.15.0; extra == "monitoring"
Requires-Dist: tensorboard>=2.13.0; extra == "monitoring"
Requires-Dist: mlflow>=2.5.0; extra == "monitoring"
Provides-Extra: all
Requires-Dist: llmbuilder[dev,docs,gpu,monitoring]; extra == "all"
